google_air_quality_api/__init__.py
google_air_quality_api/api.py
google_air_quality_api/auth.py
google_air_quality_api/const.py
google_air_quality_api/exceptions.py
google_air_quality_api/mapping.py
google_air_quality_api/model.py
google_air_quality_api/pollutants.py
google_air_quality_api/py.typed
google_air_quality_api-3.0.0.dist-info/METADATA
google_air_quality_api-3.0.0.dist-info/WHEEL
google_air_quality_api-3.0.0.dist-info/licenses/LICENSE
google_air_quality_api-3.0.0.dist-info/RECORD
