Metadata-Version: 2.4
Name: google_air_quality_api
Version: 3.0.0
Summary: Python module to talk to Google Air Quality API.
License: MIT
License-File: LICENSE
Author: Thomas Peter Protzner
Author-email: thomas.protzner@gmail.com
Requires-Python: >=3.11
Classifier: License :: OSI Approved :: MIT License
Classifier: Programming Language :: Python :: 3
Classifier: Programming Language :: Python :: 3.11
Classifier: Programming Language :: Python :: 3.12
Classifier: Programming Language :: Python :: 3.13
Classifier: Programming Language :: Python :: 3.14
Requires-Dist: aiohttp (>=3.9.3,<4.0.0)
Requires-Dist: mashumaro (>=3.12,<4.0.0)
Project-URL: Documentation, https://github.com/Thomas55555/python-google-air-quality-api
Project-URL: Homepage, https://github.com/Thomas55555/python-google-air-quality-api
Project-URL: Issues, https://github.com/Thomas55555/aioautomower/issues
Project-URL: Repository, https://github.com/Thomas55555/python-google-air-quality-api
